{
    "homeManager": {
        "branch": "master",
        "description": "Manage a user environment using Nix  [maintainer=@rycee] ",
        "homepage": "https://nix-community.github.io/home-manager/",
        "owner": "nix-community",
        "repo": "home-manager",
        "rev": "406eeec0b98903561767ce7aca311034d298d53e",
        "sha256": "12ny9hzmpqb7g6qyvkajcxs6niq7j71i6md1la1s4rn9r75pzmdm",
        "type": "tarball",
        "url": "https://github.com/nix-community/home-manager/archive/406eeec0b98903561767ce7aca311034d298d53e.tar.gz",
        "url_template": "https://github.com/<owner>/<repo>/archive/<rev>.tar.gz"
    },
    "makes": {
        "branch": "main",
        "description": "A DevSecOps framework powered by Nix.",
        "homepage": "",
        "owner": "fluidattacks",
        "repo": "makes",
        "rev": "27f7fdb09400295a4fa58f2a9ccdac97c8f26d8c",
        "sha256": "1d4p7nlff0zvahhyd3i63wcxla6m52wjzs40wzsy6qccjcv3a0nf",
        "type": "tarball",
        "url": "https://github.com/fluidattacks/makes/archive/27f7fdb09400295a4fa58f2a9ccdac97c8f26d8c.tar.gz",
        "url_template": "https://github.com/<owner>/<repo>/archive/<rev>.tar.gz"
    },
    "nixpkgs": {
        "branch": "nixpkgs-unstable",
        "description": "Nix Packages collection",
        "homepage": "",
        "owner": "nixos",
        "repo": "nixpkgs",
        "rev": "0920efc96dc2474295f17ae9f71da5baf621246e",
        "sha256": "0drhack8k6aw6z74dpwi4xrmz1y72yradpx7f555867c437iwp5y",
        "type": "tarball",
        "url": "https://github.com/nixos/nixpkgs/archive/0920efc96dc2474295f17ae9f71da5baf621246e.tar.gz",
        "url_template": "https://github.com/<owner>/<repo>/archive/<rev>.tar.gz"
    },
    "nixpkgsNixos": {
        "branch": "nixos-21.05",
        "description": "Nix Packages collection",
        "homepage": "",
        "owner": "nixos",
        "repo": "nixpkgs",
        "rev": "95eed9b64eee24975b880308065654fd059f22c3",
        "sha256": "1x59xdxh2vrnhh4j29nyq7npq70v178j5acdm2zsgamcagm3qif9",
        "type": "tarball",
        "url": "https://github.com/nixos/nixpkgs/archive/95eed9b64eee24975b880308065654fd059f22c3.tar.gz",
        "url_template": "https://github.com/<owner>/<repo>/archive/<rev>.tar.gz"
    },
    "nixpkgsTimedoctor": {
        "branch": "master",
        "description": "Nix Packages collection",
        "homepage": "",
        "owner": "nixos",
        "repo": "nixpkgs",
        "rev": "7310407d493ee1c7caf38f8181507d7ac9c90eb8",
        "sha256": "1fwqfl3l5pip9ngyln7kanka5m0xlx8v5n4jbk88mn5zrn8psdyz",
        "type": "tarball",
        "url": "https://github.com/nixos/nixpkgs/archive/7310407d493ee1c7caf38f8181507d7ac9c90eb8.tar.gz",
        "url_template": "https://github.com/<owner>/<repo>/archive/<rev>.tar.gz"
    },
    "product": {
        "branch": "master",
        "repo": "https://gitlab.com/fluidattacks/product",
        "rev": "26f359fa84733da7fa8a34a8b9fae33b5132c069",
        "type": "git"
    },
    "pythonOnNix": {
        "branch": "main",
        "description": "Extensive collection of Python packages from PyPI, for Nix",
        "homepage": null,
        "owner": "kamadorueda",
        "repo": "python-on-nix",
        "rev": "910d3f6554acd4a4ef0425ebccd31104dccb283c",
        "sha256": "191l3ncl4mwl5w5rby59k2gnjz0qrllxay6cm3vdfszlhk6p03r7",
        "type": "tarball",
        "url": "https://github.com/kamadorueda/python-on-nix/archive/910d3f6554acd4a4ef0425ebccd31104dccb283c.tar.gz",
        "url_template": "https://github.com/<owner>/<repo>/archive/<rev>.tar.gz"
    },
    "timedoctor": {
        "sha256": "1d86hibgbr4mhcfvapk6ibzrqpdiwagp6dhq6s2g88829x7skh6a",
        "type": "file",
        "url": "https://repo2.timedoctor.com/td-desktop-hybrid/prod/v3.12.13/timedoctor-desktop_3.12.13_linux-x86_64.AppImage",
        "url_template": "https://repo2.timedoctor.com/td-desktop-hybrid/prod/v<version>/timedoctor-desktop_<version>_linux-x86_64.AppImage",
        "version": "3.12.13"
    }
}
